hyimage/common/constants.py
hyimage/common/format_prompt.py
hyimage/common/config/__init__.py
hyimage/common/config/base_config.py
hyimage/common/config/lazy.py
hyimage/diffusion/cfg_utils.py
hyimage/diffusion/pipelines/__init__.py
hyimage/diffusion/pipelines/hunyuanimage_pipeline.py
hyimage/diffusion/pipelines/hunyuanimage_refiner_pipeline.py
hyimage/models/model_zoo.py
hyimage/models/hunyuan/__init__.py
hyimage/models/hunyuan/configs/hunyuanimage_config.py
hyimage/models/hunyuan/modules/__init__.py
hyimage/models/hunyuan/modules/activation_layers.py
hyimage/models/hunyuan/modules/embed_layers.py
hyimage/models/hunyuan/modules/flash_attn_no_pad.py
hyimage/models/hunyuan/modules/hunyuanimage_dit.py
hyimage/models/hunyuan/modules/mlp_layers.py
hyimage/models/hunyuan/modules/models.py
hyimage/models/hunyuan/modules/modulate_layers.py
hyimage/models/hunyuan/modules/norm_layers.py
hyimage/models/hunyuan/modules/posemb_layers.py
hyimage/models/hunyuan/modules/token_refiner.py
hyimage/models/hunyuan/utils/__init__.py
hyimage/models/hunyuan/utils/helpers.py
hyimage/models/reprompt/__init__.py
hyimage/models/reprompt/reprompt.py
hyimage/models/text_encoder/__init__.py
hyimage/models/text_encoder/byT5/__init__.py
hyimage/models/vae/__init__.py
hyimage/models/vae/hunyuanimage_vae.py
hyimage/models/vae/refiner_vae.py
hyimage-0.0.2.dist-info/licenses/LICENSE
hyimage-0.0.2.dist-info/licenses/NOTICE
hyimage-0.0.2.dist-info/METADATA
hyimage-0.0.2.dist-info/WHEEL
hyimage-0.0.2.dist-info/top_level.txt
hyimage-0.0.2.dist-info/RECORD
