Metadata-Version: 2.4
Name: hyimage
Version: 0.0.2
Summary: hyimage
Author-email: Yinchu Xia <sales@pytorchsoft.com>
Project-URL: Homepage, https://github.com/pytorchsoft/abao_ai
Project-URL: Issues, https://github.com/pytorchsoft/abao_ai/issues
Classifier: Programming Language :: Python :: 3
Classifier: Operating System :: POSIX :: Linux
Requires-Python: >=3.9
License-File: LICENSE
License-File: NOTICE
Requires-Dist: tqdm
Requires-Dist: torch
Requires-Dist: einops
Requires-Dist: loguru
Requires-Dist: numpy
Requires-Dist: pillow
Requires-Dist: omegaconf
Requires-Dist: diffusers
Requires-Dist: safetensors
Requires-Dist: torchvision
Requires-Dist: transformers
Requires-Dist: wheel
Requires-Dist: setuptools
Requires-Dist: modelscope
Requires-Dist: huggingface_hub[cli]
Dynamic: license-file
